kaiowa/__init__.py
kaiowa/backends/__init__.py
kaiowa/core/__init__.py
kaiowa/core/selectables.py
kaiowa/core/utils.py
kaiowa/exceptions.py
kaiowa/migrations/__init__.py
kaiowa/orm/__init__.py
kaiowa-0.1.0.dist-info/LICENSE
kaiowa-0.1.0.dist-info/WHEEL
kaiowa-0.1.0.dist-info/METADATA
kaiowa-0.1.0.dist-info/RECORD
