Metadata-Version: 2.1
Name: kaiowa
Version: 0.1.0
Summary: Asynchronous Database ORM for Python.
License: MIT
Author: Eduardo Rezende
Author-email: eduardorbr7@gmail.com
Requires-Python: >=3.8,<4.0
Classifier: License :: OSI Approved :: MIT License
Classifier: Programming Language :: Python :: 3
Classifier: Programming Language :: Python :: 3.8
Classifier: Programming Language :: Python :: 3.9
